nekhebet_core/__init__.py
nekhebet_core/canonical.py
nekhebet_core/config.py
nekhebet_core/envelope.py
nekhebet_core/metrics.py
nekhebet_core/registry.py
nekhebet_core/replay_guard.py
nekhebet_core/serialization.py
nekhebet_core/signing.py
nekhebet_core/types.py
nekhebet_core/utils.py
nekhebet_core/verification.py
nekhebet_core-4.0.0.dist-info/METADATA
nekhebet_core-4.0.0.dist-info/WHEEL
nekhebet_core-4.0.0.dist-info/top_level.txt
nekhebet_core-4.0.0.dist-info/RECORD
