Metadata-Version: 2.4
Name: nekhebet-core
Version: 4.0.0
Summary: Nekhebet Core — canonical signed event system
Requires-Python: >=3.10
Requires-Dist: msgspec>=0.18
Requires-Dist: cryptography>=42.0.0
